retry_toolkit/__about__.py
retry_toolkit/__init__.py
retry_toolkit/_utils.py
retry_toolkit/async_core.py
retry_toolkit/backoff.py
retry_toolkit/constants.py
retry_toolkit/core.py
retry_toolkit/defaults.py
retry_toolkit/exceptions.py
retry_toolkit/simple.py
retry_toolkit-0.6.1.dist-info/METADATA
retry_toolkit-0.6.1.dist-info/WHEEL
retry_toolkit-0.6.1.dist-info/licenses/LICENSE
retry_toolkit-0.6.1.dist-info/RECORD
