Metadata-Version: 2.4
Name: retry-toolkit
Version: 0.6.1
Summary: Yet another retry implementation.
Project-URL: Documentation, https://davidejames.github.io/retry-toolkit/
Project-URL: Issues, https://github.com/davidejames/retry-toolkit/issues
Project-URL: Source, https://github.com/davidejames/retry-toolkit
Author-email: "David E. James" <david.eugene.james@protonmail.com>
License-Expression: MIT
License-File: LICENSE
Classifier: Development Status :: 4 - Beta
Classifier: Programming Language :: Python
Classifier: Programming Language :: Python :: 3.8
Classifier: Programming Language :: Python :: 3.9
Classifier: Programming Language :: Python :: 3.10
Classifier: Programming Language :: Python :: 3.11
Classifier: Programming Language :: Python :: 3.12
Classifier: Programming Language :: Python :: Implementation :: CPython
Classifier: Programming Language :: Python :: Implementation :: PyPy
Requires-Python: >=3.8
